Workbook

Sheet group info
A1: Old label | B1: New label | C1: SOCyear | D1: Proposed description | E1: Possible alternate description | F1: General info for each group of lookups
A2: Construction | B2: Construction | C2: 2010 | D2: Construction 'priority sector' workforce (based on SOC2010) | E2: Priority sector workforce identified by the government Sector Delivery Lead for Construction (based on SOC2010 occupations) | F2: Priority sector workforce occupations identified by government Sector Delivery Leads; these are based on SOC2010. [add list]
A3: Digital and technology | B3: Digital and technology | C3: 2010 | D3: Digital and technology 'priority sector' workforce (based on SOC2010) | E3: Priority sector workforce identified by the government Sector Delivery Lead for Digital and Technology (based on SOC2010 occupations)
A4: Green | B4: Green | C4: 2020 | D4: Most important occupations in the key sectors for delivering net zero targets (based on SOC2020)
A5: Green | B5: Green | C5: 2010 | D5: Most important occupations in the key sectors for delivering net zero targets (based on SOC2010)
A6: Haulage and logistics | B6: Haulage and logistics | C6: 2010 | D6: Haulage and logistics 'priority sector' workforce (based on SOC2010) | E6: Priority sector workforce identified by the government Sector Delivery Lead for Haulage and Logistics (based on SOC2010 occupations)
A7: Health and social care | B7: Health and social care | C7: 2010 | D7: Health and social care 'priority sector' workforce (based on SOC2010) | E7: Priority sector workforce identified by the government Sector Delivery Lead for Health and Social Care (based on SOC2010 occupations)
A8: Manufacturing | B8: Manufacturing | C8: 2010 | D8: Manufacturing 'priority sector' workforce (based on SOC2010) | E8: Priority sector workforce identified by the government Sector Delivery Lead for Manufacturing (based on SOC2010 occupations)
A9: STEM: core | B9: STEM | C9: 2020 | D9: Science', 'Engineering and Technology' and 'Mathematics' occupations identified by the Royal Society (based on SOC2020) | E9: Core list of STEM occupations identified by…. - does not incude 'medicine & health' or 'teaching' (based on SOC2020) | F9: STEM occupations identified by the Royal Society, as part of XXX; there are versions of these groups based on each of SOC2010 and SOC2020.
A10: STEM: core | B10: STEM | C10: 2010 | D10: Science', 'Engineering and Technology' and 'Mathematics' occupations identified by the Royal Society (based on SOC2010) | E10: Core list of STEM occupations identified by…. - does not incude 'medicine & health' or 'teaching' (based on SOC2010)
A11: STEM: core STEM with medicine and health & teaching | B11: STEM plus medicine and health and other | C11: 2020 | D11: Science', 'Engineering and Technology' and 'Mathematics' occupations plus 'Medicine and Health' and 'Teaching' occupations identified by the Royal Society (based on SOC2020) | E11: Full list of STEM occupations, including 'medicine and health' and teaching, identified by…. (based on SOC2020)
A12: STEM: core STEM with medicine and health & teaching | B12: STEM plus medicine and health and other | C12: 2010 | D12: Science', 'Engineering and Technology' and 'Mathematics' occupations plus 'Medicine and Health' and 'Teaching' occupations identified by the Royal Society (based on SOC2010) | E12: Full list of STEM occupations, including 'medicine and health' and teaching, identified by…. (based on SOC2010)
A13: STEM: DSCET | B13: STEM: DCSET | C13: 2020 | D13: Digital and computing STEM occupations identified by the Digital and Computing Skills Education Taskforce (based on SOC2020) | E13: Digital and computing STEM occupations identified by the DCSET (based on SOC2020) | F13: Digital and computing occupations identifie`d on SOC2020 and are a subset of the STEM occupations.
A14: STEM: NSTC - AI | B14: STEM: AI | C14: 2020 | D14: Artifical Intelligence technology STEM occupations identified as most relevant by DSIT critical tech policy teams (based on SOC2020) | E14: Artifical Intelligence technology STEM occupations (based on SOC2020) | F14: Critical technology occupations identified by DSIT policy teams, produced as part of XXXX; these are based on SOC2020 and are a subset of the STEM occupautions.
A15: STEM: NSTC - Eng Bio | B15: STEM: Eng Bio | C15: 2020 | D15: Engineering Biology STEM occupations identified as most relevant by DSIT critical tech policy teams (based on SOC2020) | E15: Engineering Biology technology STEM occupations (based on SOC2020)
A16: STEM: NSTC - Future Telecoms | B16: STEM: Future Telecoms | C16: 2020 | D16: Future Telecoms STEM occupations identified as most relevant by DSIT critical tech policy teams (based on SOC2020) | E16: Futute Telecommunications technology STEM occupations (based on SOC2020)
A17: STEM: NSTC - Quantum | B17: STEM: Quantum | C17: 2020 | D17: Quantum technology STEM occupations identified as most relevant by DSIT critical tech policy teams (based on SOC2020) | E17: Quantum technology STEM occupations (based on SOC2020)
A18: STEM: NSTC - Semiconductors | B18: STEM: Semiconductors | C18: 2020 | D18: Semiconductors technology STEM occupations identified as most relevant by DSIT critical tech policy teams (based on SOC2020) | E18: Semiconductors technology STEM occupations (based on SOC2020)
A19: STEM: NSTC - all | B19: STEM: Critical technology key occupations | C19: 2020 | D19: Occupations identified as key to each of the 5 critical technologies by DSIT critical technology policy teams (based on SOC2020)
A20: STEM: NSTC - all | B20: STEM: Critical technology key occupations | C20: 2010 | D20: Occupations identified as key to each of the 5 critical technologies by DSIT critical technology policy teams (based on SOC2010)
B22: Q: should SDL groups be prefixed with SDL? | D22: Q for Hannah: do we want to add SDL into the description for SDL groups?

Sheet sectorLookup
A1: SOCcode | B1: SOCdesc | C1: oldSector | D1: Sector | E1: Source | F1: SOCyear | G1: SectorSocYear
A2: 1121 | B2: =IF(F2=2020,INDEX(SOC2020_Structure!E:E,MATCH(sectorLookup!A2,SOC2020_Structure!D:D,0)),INDEX(SOC2010_Structure!E:E,MATCH(sectorLookup!A2,SOC2010_Structure!D:D,0))) -> Production managers and directors in manufacturing | C2: Manufacturing | D2: =INDEX('group info'!B:B,MATCH(sectorLookup!C2,'group info'!A:A,0)) -> Manufacturing | E2: SDL List | F2: 2010 | G2: =D2&" SOC"&F2 -> Manufacturing SOC2010
A3: 1122 | B3: =IF(F3=2020,INDEX(SOC2020_Structure!E:E,MATCH(sectorLookup!A3,SOC2020_Structure!D:D,0)),INDEX(SOC2010_Structure!E:E,MATCH(sectorLookup!A3,SOC2010_Structure!D:D,0))) -> Production managers and directors in construction | C3: Construction | D3: =INDEX('group info'!B:B,MATCH(sectorLookup!C3,'group info'!A:A,0)) -> Construction | E3: SDL List | F3: 2010 | G3: =D3&" SOC"&F3 -> Construction SOC2010
A4: 1123 | B4: =IF(F4=2020,INDEX(SOC2020_Structure!E:E,MATCH(sectorLookup!A4,SOC2020_Structure!D:D,0)),INDEX(SOC2010_Structure!E:E,MATCH(sectorLookup!A4,SOC2010_Structure!D:D,0))) -> Production managers and directors in mining and energy | C4: Manufacturing | D4: =INDEX('group info'!B:B,MATCH(sectorLookup!C4,'group info'!A:A,0)) -> Manufacturing | E4: SDL List | F4: 2010 | G4: =D4&" SOC"&F4 -> Manufacturing SOC2010
A5: 1136 | B5: =IF(F5=2020,INDEX(SOC2020_Structure!E:E,MATCH(sectorLookup!A5,SOC2020_Structure!D:D,0)),INDEX(SOC2010_Structure!E:E,MATCH(sectorLookup!A5,SOC2010_Structure!D:D,0))) -> Information technology and telecommunications directors | C5: Digital and technology | D5: =INDEX('group info'!B:B,MATCH(sectorLookup!C5,'group info'!A:A,0)) -> Digital and technology | E5: SDL List | F5: 2010 | G5: =D5&" SOC"&F5 -> Digital and technology SOC2010
A6: 1161 | B6: =IF(F6=2020,INDEX(SOC2020_Structure!E:E,MATCH(sectorLookup!A6,SOC2020_Structure!D:D,0)),INDEX(SOC2010_Structure!E:E,MATCH(sectorLookup!A6,SOC2010_Structure!D:D,0))) -> Managers and directors in transport and distribution | C6: Haulage and logistics | D6: =INDEX('group info'!B:B,MATCH(sectorLookup!C6,'group info'!A:A,0)) -> Haulage and logistics | E6: SDL List | F6: 2010 | G6: =D6&" SOC"&F6 -> Haulage and logistics SOC2010
A7: 1181 | B7: =IF(F7=2020,INDEX(SOC2020_Structure!E:E,MATCH(sectorLookup!A7,SOC2020_Structure!D:D,0)),INDEX(SOC2010_Structure!E:E,MATCH(sectorLookup!A7,SOC2010_Structure!D:D,0))) -> Health services and public health managers and directors | C7: Health and social care | D7: =INDEX('group info'!B:B,MATCH(sectorLookup!C7,'group info'!A:A,0)) -> Health and social care | E7: SDL List | F7: 2010 | G7: =D7&" SOC"&F7 -> Health and social care SOC2010
A8: 1184 | B8: =IF(F8=2020,INDEX(SOC2020_Structure!E:E,MATCH(sectorLookup!A8,SOC2020_Structure!D:D,0)),INDEX(SOC2010_Structure!E:E,MATCH(sectorLookup!A8,SOC2010_Structure!D:D,0))) -> Social services managers and directors | C8: Health and social care | D8: =INDEX('group info'!B:B,MATCH(sectorLookup!C8,'group info'!A:A,0)) -> Health and social care | E8: SDL List | F8: 2010 | G8: =D8&" SOC"&F8 -> Health and social care SOC2010
A9: 1241 | B9: =IF(F9=2020,INDEX(SOC2020_Structure!E:E,MATCH(sectorLookup!A9,SOC2020_Structure!D:D,0)),INDEX(SOC2010_Structure!E:E,MATCH(sectorLookup!A9,SOC2010_Structure!D:D,0))) -> Health care practice managers | C9: Health and social care | D9: =INDEX('group info'!B:B,MATCH(sectorLookup!C9,'group info'!A:A,0)) -> Health and social care | E9: SDL List | F9: 2010 | G9: =D9&" SOC"&F9 -> Health and social care SOC2010
A10: 1242 | B10: =IF(F10=2020,INDEX(SOC2020_Structure!E:E,MATCH(sectorLookup!A10,SOC2020_Structure!D:D,0)),INDEX(SOC2010_Structure!E:E,MATCH(sectorLookup!A10,SOC2010_Structure!D:D,0))) -> Residential, day and domiciliary care managers and proprietors | C10: Health and social care | D10: =INDEX('group info'!B:B,MATCH(sectorLookup!C10,'group info'!A:A,0)) -> Health and social care | E10: SDL List | F10: 2010 | G10: =D10&" SOC"&F10 -> Health and social care SOC2010
A11: 1252 | B11: =IF(F11=2020,INDEX(SOC2020_Structure!E:E,MATCH(sectorLookup!A11,SOC2020_Structure!D:D,0)),INDEX(SOC2010_Structure!E:E,MATCH(sectorLookup!A11,SOC2010_Structure!D:D,0))) -> Garage managers and proprietors | C11: Haulage and logistics | D11: =INDEX('group info'!B:B,MATCH(sectorLookup!C11,'group info'!A:A,0)) -> Haulage and logistics | E11: SDL List | F11: 2010 | G11: =D11&" SOC"&F11 -> Haulage and logistics SOC2010
A12: 2121 | B12: =IF(F12=2020,INDEX(SOC2020_Structure!E:E,MATCH(sectorLookup!A12,SOC2020_Structure!D:D,0)),INDEX(SOC2010_Structure!E:E,MATCH(sectorLookup!A12,SOC2010_Structure!D:D,0))) -> Civil engineers | C12: Construction | D12: =INDEX('group info'!B:B,MATCH(sectorLookup!C12,'group info'!A:A,0)) -> Construction | E12: SDL List | F12: 2010 | G12: =D12&" SOC"&F12 -> Construction SOC2010
A13: 2122 | B13: =IF(F13=2020,INDEX(SOC2020_Structure!E:E,MATCH(sectorLookup!A13,SOC2020_Structure!D:D,0)),INDEX(SOC2010_Structure!E:E,MATCH(sectorLookup!A13,SOC2010_Structure!D:D,0))) -> Mechanical engineers | C13: Construction | D13: =INDEX('group info'!B:B,MATCH(sectorLookup!C13,'group info'!A:A,0)) -> Construction | E13: SDL List | F13: 2010 | G13: =D13&" SOC"&F13 -> Construction SOC2010
... A1192: 8133 | B1192: =IF(F1192=2020,INDEX(SOC2020_Structure!E:E,MATCH(sectorLookup!A1192,SOC2020_Structure!D:D,0)),INDEX(SOC2010_Structure!E:E,MATCH(sectorLookup!A1192,SOC2010_Structure!D:D,0))) -> Routine inspectors and testers | C1192: STEM: NSTC - all | D1192: =INDEX('group info'!B:B,MATCH(sectorLookup!C1192,'group info'!A:A,0)) -> STEM: Critical technology key occupations | E1192: UFS STEM list | F1192: 2010 | G1192: =D1192&" SOC"&F1192 -> STEM: Critical technology key occupations SOC2010

Sheet sectorDescriptions
A1: SectorSocYear | B1: New label | C1: SOCyear | D1: Description
A2: =B2&" SOC"&C2 -> Construction SOC2010 | B2: Construction | C2: 2010 | D2: Construction 'priority sector' workforce (based on SOC2010)
A3: =B3&" SOC"&C3 -> Digital and technology SOC2010 | B3: Digital and technology | C3: 2010 | D3: Digital and technology 'priority sector' workforce (based on SOC2010)
A4: =B4&" SOC"&C4 -> Green SOC2020 | B4: Green | C4: 2020 | D4: Most important occupations in the key sectors for delivering net zero targets (based on SOC2020)
A5: =B5&" SOC"&C5 -> Green SOC2010 | B5: Green | C5: 2010 | D5: Most important occupations in the key sectors for delivering net zero targets (based on SOC2010)
A6: =B6&" SOC"&C6 -> Haulage and logistics SOC2010 | B6: Haulage and logistics | C6: 2010 | D6: Haulage and logistics 'priority sector' workforce (based on SOC2010)
A7: =B7&" SOC"&C7 -> Health and social care SOC2010 | B7: Health and social care | C7: 2010 | D7: Health and social care 'priority sector' workforce (based on SOC2010)
A8: =B8&" SOC"&C8 -> Manufacturing SOC2010 | B8: Manufacturing | C8: 2010 | D8: Manufacturing 'priority sector' workforce (based on SOC2010)
A9: =B9&" SOC"&C9 -> STEM SOC2020 | B9: STEM | C9: 2020 | D9: 'Science', 'Engineering and Technology' and 'Mathematics' occupations identified by the Royal Society (based on SOC2020)
A10: =B10&" SOC"&C10 -> STEM SOC2010 | B10: STEM | C10: 2010 | D10: 'Science', 'Engineering and Technology' and 'Mathematics' occupations identified by the Royal Society (based on SOC2010)
A11: =B11&" SOC"&C11 -> STEM plus medicine and health and other SOC2020 | B11: STEM plus medicine and health and other | C11: 2020 | D11: 'Science', 'Engineering and Technology' and 'Mathematics' occupations plus 'Medicine and Health' and 'Teaching' occupations identified by the Royal Society (based on SOC2020)
A12: =B12&" SOC"&C12 -> STEM plus medicine and health and other SOC2010 | B12: STEM plus medicine and health and other | C12: 2010 | D12: 'Science', 'Engineering and Technology' and 'Mathematics' occupations plus 'Medicine and Health' and 'Teaching' occupations identified by the Royal Society (based on SOC2010)
A13: =B13&" SOC"&C13 -> STEM: DCSET SOC2020 | B13: STEM: DCSET | C13: 2020 | D13: Digital and computing STEM occupations identified by the Digital and Computing Skills Education Taskforce (based on SOC2020)
... A20: =B20&" SOC"&C20 -> STEM: Critical technology key occupations SOC2010 | B20: STEM: Critical technology key occupations | C20: 2010 | D20: Occupations identified as key to each of the 5 critical technologies by DSIT critical technology policy teams (based on SOC2010)

Sheet SOC2020_Structure
A1: SOC2020 Major Group | B1: SOC2020 Sub-Major Group | C1: SOC2020 Minor Group | D1: SOC2020 Unit Group | E1: SOC2020 Group Title | F1: Change | G1: Date
A2: 1 | E2: MANAGERS, DIRECTORS AND SENIOR OFFICIALS
B4: 11 | E4: CORPORATE MANAGERS AND DIRECTORS
C6: 111 | E6: Chief Executives and Senior Officials
D8: 1111 | E8: Chief executives and senior officials
D9: 1112 | E9: Elected officers and representatives
C11: 112 | E11: Production Managers and Directors
D13: 1121 | E13: Production managers and directors in manufacturing
D14: 1122 | E14: Production managers and directors in construction
D15: 1123 | E15: Production managers and directors in mining and energy
C17: 113 | E17: Functional Managers and Directors
D19: 1131 | E19: Financial managers and directors
D20: 1132 | E20: Marketing, sales and advertising directors
D21: 1133 | E21: Public relations and communications directors
D22: 1134 | E22: Purchasing managers and directors
D23: 1135 | E23: Charitable organisation managers and directors
D24: 1136 | E24: Human resource managers and directors
D25: 1137 | E25: Information technology managers directors
D26: 1139 | E26: Functional managers and directors n.e.c.
C28: 114 | E28: Directors in Logistics, Warehousing and Transport
D30: 1140 | E30: Directors in logistics, warehousing and transport
C32: 115 | E32: Managers and Directors in Retail and Wholesale
D34: 1150 | E34: Managers and directors in retail and wholesale
C36: 116 | E36: Senior Officers in Protective Services
D38: 1161 | E38: Officers in armed forces
D39: 1162 | E39: Senior police officers
D40: 1163 | E40: Senior officers in fire, ambulance, prison and related services
C42: 117 | E42: Health and Social Services Managers and Directors
D44: 1171 | E44: Health services and public health managers and directors
D45: 1172 | E45: Social services managers and directors
B47: 12 | E47: OTHER MANAGERS AND PROPRIETORS
C49: 121 | E49: Managers and Proprietors in Agriculture Related Services
D51: 1211 | E51: Managers and proprietors in agriculture and horticulture
D52: 1212 | E52: Managers and proprietors in forestry, fishing and related services
C54: 122 | E54: Managers and Proprietors in Hospitality and Leisure Services
D56: 1221 | E56: Hotel and accommodation managers and proprietors
D57: 1222 | E57: Restaurant and catering establishment managers and proprietors
D58: 1223 | E58: Publicans and managers of licensed premises
D59: 1224 | E59: Leisure and sports managers and proprietors | F59: Unit group name was Leisure and sports managers | G59: 44799
D60: 1225 | E60: Travel agency managers and proprietors
C62: 123 | E62: Managers and Proprietors in Health and Care Services
D64: 1231 | E64: Health care practice managers
D65: 1232 | E65: Residential, day and domiciliary care managers and proprietors
D66: 1233 | E66: Early education and childcare services proprietors
C68: 124 | E68: Managers in Logistics, Warehousing and Transport
D70: 1241 | E70: Managers in transport and distribution
D71: 1242 | E71: Managers in storage and warehousing
D72: 1243 | E72: Managers in logistics
C74: 125 | E74: Managers and Proprietors in Other Services
D76: 1251 | E76: Property, housing and estate managers
D77: 1252 | E77: Garage managers and proprietors
D78: 1253 | E78: Hairdressing and beauty salon managers and proprietors
D79: 1254 | E79: Waste disposal and environmental services managers
D80: 1255 | E80: Managers and directors in the creative industries
D81: 1256 | E81: Betting shop and gambling establishment managers
D82: 1257 | E82: Hire services managers and proprietors
D83: 1258 | E83: Directors in consultancy services
D84: 1259 | E84: Managers and proprietors in other services n.e.c.
A86: 2 | E86: PROFESSIONAL OCCUPATIONS
B88: 21 | E88: SCIENCE, RESEARCH, ENGINEERING AND TECHNOLOGY PROFESSIONALS
C90: 211 | E90: Natural and Social Science Professionals
D92: 2111 | E92: Chemical scientists
D93: 2112 | E93: Biological scientists
D94: 2113 | E94: Biochemists and biomedical scientists
D95: 2114 | E95: Physical scientists
D96: 2115 | E96: Social and humanities scientists
D97: 2119 | E97: Natural and social science professionals n.e.c.
C99: 212 | E99: Engineering Professionals
D101: 2121 | E101: Civil engineers
D102: 2122 | E102: Mechanical engineers
D103: 2123 | E103: Electrical engineers
D104: 2124 | E104: Electronics engineers
D105: 2125 | E105: Production and process engineers
D106: 2126 | E106: Aerospace engineers
D107: 2127 | E107: Engineering project managers and project engineers
D108: 2129 | E108: Engineering professionals n.e.c.
C110: 213 | E110: Information Technology Professionals
D112: 2131 | E112: IT project managers
D113: 2132 | E113: IT managers
D114: 2133 | E114: IT business analysts, architects and systems designers
D115: 2134 | E115: Programmers and software development professionals
D116: 2135 | E116: Cyber security professionals
D117: 2136 | E117: IT quality and testing professionals
D118: 2137 | E118: IT network professionals
D119: 2139 | E119: Information technology professionals n.e.c.
C121: 214 | E121: Web and Multimedia Design Professionals
D123: 2141 | E123: Web design professionals
D124: 2142 | E124: Graphic and multimedia designers
C126: 215 | E126: Conservation and Environment Professionals
D128: 2151 | E128: Conservation professionals
D129: 2152 | E129: Environment professionals
C131: 216 | E131: Research and Development (R&D) and Other Research Professionals
D133: 2161 | E133: Research and development (R&D) managers
D134: 2162 | E134: Other researchers, unspecified discipline
B136: 22 | E136: HEALTH PROFESSIONALS
C138: 221 | E138: Medical Practitioners
D140: 2211 | E140: Generalist medical practitioners
D141: 2212 | E141: Specialist medical practitioners
C143: 222 | E143: Therapy Professionals
D145: 2221 | E145: Physiotherapists
...

Sheet SOC2010_Structure
A1: Major Group | B1: Sub-Major Group | C1: Minor Group | D1: Unit Group | E1: Group Title
A3: 1 | E3: MANAGERS, DIRECTORS AND SENIOR OFFICIALS
B5: 11 | E5: CORPORATE MANAGERS AND DIRECTORS
C7: 111 | E7: Chief Executives and Senior Officials
D9: 1115 | E9: Chief executives and senior officials
D10: 1116 | E10: Elected officers and representatives
C12: 112 | E12: Production Managers and Directors
D14: 1121 | E14: Production managers and directors in manufacturing
D15: 1122 | E15: Production managers and directors in construction
D16: 1123 | E16: Production managers and directors in mining and energy
C18: 113 | E18: Functional Managers and Directors
D20: 1131 | E20: Financial managers and directors
D21: 1132 | E21: Marketing and sales directors
D22: 1133 | E22: Purchasing managers and directors
D23: 1134 | E23: Advertising and public relations directors
D24: 1135 | E24: Human resource managers and directors
D25: 1136 | E25: Information technology and telecommunications directors
D26: 1139 | E26: Functional managers and directors n.e.c.
C28: 115 | E28: Financial Institution Managers and Directors
D30: 1150 | E30: Financial institution managers and directors
C32: 116 | E32: Managers and Directors in Transport and Logistics
D34: 1161 | E34: Managers and directors in transport and distribution
D35: 1162 | E35: Managers and directors in storage and warehousing
C37: 117 | E37: Senior Officers in Protective Services
D39: 1171 | E39: Officers in armed forces
D40: 1172 | E40: Senior police officers
D41: 1173 | E41: Senior officers in fire, ambulance, prison and related services
C43: 118 | E43: Health and Social Services Managers and Directors
D45: 1181 | E45: Health services and public health managers and directors
D46: 1184 | E46: Social services managers and directors
C48: 119 | E48: Managers and Directors in Retail and Wholesale
D50: 1190 | E50: Managers and directors in retail and wholesale
B52: 12 | E52: OTHER MANAGERS AND PROPRIETORS
C54: 121 | E54: Managers and Proprietors in Agriculture Related Services
D56: 1211 | E56: Managers and proprietors in agriculture and horticulture
D57: 1213 | E57: Managers and proprietors in forestry, fishing and related services
C59: 122 | E59: Managers and Proprietors in Hospitality and Leisure Services
D61: 1221 | E61: Hotel and accommodation managers and proprietors
D62: 1223 | E62: Restaurant and catering establishment managers and proprietors
D63: 1224 | E63: Publicans and managers of licensed premises
D64: 1225 | E64: Leisure and sports managers
D65: 1226 | E65: Travel agency managers and proprietors
C67: 124 | E67: Managers and Proprietors in Health and Care Services
D69: 1241 | E69: Health care practice managers
D70: 1242 | E70: Residential, day and domiciliary care managers and proprietors
C72: 125 | E72: Managers and Proprietors in Other Services
D74: 1251 | E74: Property, housing and estate managers
D75: 1252 | E75: Garage managers and proprietors
D76: 1253 | E76: Hairdressing and beauty salon managers and proprietors
D77: 1254 | E77: Shopkeepers and proprietors – wholesale and retail
D78: 1255 | E78: Waste disposal and environmental services managers
D79: 1259 | E79: Managers and proprietors in other services n.e.c.
A81: 2 | E81: PROFESSIONAL OCCUPATIONS
B83: 21 | E83: SCIENCE, RESEARCH, ENGINEERING AND TECHNOLOGY PROFESSIONALS
C85: 211 | E85: Natural and Social Science Professionals
D87: 2111 | E87: Chemical scientists
D88: 2112 | E88: Biological scientists and biochemists
D89: 2113 | E89: Physical scientists
D90: 2114 | E90: Social and humanities scientists
D91: 2119 | E91: Natural and social science professionals n.e.c.
C93: 212 | E93: Engineering Professionals
D95: 2121 | E95: Civil engineers
D96: 2122 | E96: Mechanical engineers
D97: 2123 | E97: Electrical engineers
D98: 2124 | E98: Electronics engineers
D99: 2126 | E99: Design and development engineers
D100: 2127 | E100: Production and process engineers
D101: 2129 | E101: Engineering professionals n.e.c.
C103: 213 | E103: Information Technology and Telecommunications Professionals
D105: 2133 | E105: IT specialist managers
D106: 2134 | E106: IT project and programme managers
D107: 2135 | E107: IT business analysts, architects and systems designers
D108: 2136 | E108: Programmers and software development professionals
D109: 2137 | E109: Web design and development professionals
D110: 2139 | E110: Information technology and telecommunications professionals n.e.c.
C112: 214 | E112: Conservation and Environment Professionals
D114: 2141 | E114: Conservation professionals
D115: 2142 | E115: Environment professionals
C117: 215 | E117: Research and Development Managers
D119: 2150 | E119: Research and development managers
B121: 22 | E121: HEALTH PROFESSIONALS
C123: 221 | E123: Health Professionals
D125: 2211 | E125: Medical practitioners
D126: 2212 | E126: Psychologists
D127: 2213 | E127: Pharmacists
D128: 2214 | E128: Ophthalmic opticians
D129: 2215 | E129: Dental practitioners
D130: 2216 | E130: Veterinarians
D131: 2217 | E131: Medical radiographers
D132: 2218 | E132: Podiatrists
D133: 2219 | E133: Health professionals n.e.c.
C135: 222 | E135: Therapy Professionals
D137: 2221 | E137: Physiotherapists
D138: 2222 | E138: Occupational therapists
D139: 2223 | E139: Speech and language therapists
D140: 2229 | E140: Therapy professionals n.e.c.
C142: 223 | E142: Nursing and Midwifery Professionals
D143: 2231 | E143: Nurses
D144: 2232 | E144: Midwives
B146: 23 | E146: TEACHING AND EDUCATIONAL PROFESSIONALS
...
